audio_denoiser/AudioDenoiser.py
audio_denoiser/helpers/audio_helper.py
audio_denoiser/helpers/torch_helper.py
audio_denoiser/modules/AudioNoiseModel.py
audio_denoiser/modules/Permute.py
audio_denoiser/modules/SimpleRoberta.py
audio_denoiser/modules/SpectrogramScaler.py
audio_denoiser/modules/View.py
audio_denoiser-0.1.2.dist-info/LICENSE.md
audio_denoiser-0.1.2.dist-info/METADATA
audio_denoiser-0.1.2.dist-info/WHEEL
audio_denoiser-0.1.2.dist-info/top_level.txt
audio_denoiser-0.1.2.dist-info/RECORD
