Metadata-Version: 2.1
Name: audio-denoiser
Version: 0.1.2
Summary: A Python library for (speech) audio denoising.
Home-page: https://github.com/jose-solorzano/audio-denoiser
Author: Jose Solorzano
Classifier: Intended Audience :: Developers
Classifier: License :: OSI Approved :: MIT License
Classifier: Topic :: Software Development :: Libraries
Classifier: Topic :: Utilities
Requires-Python: >=3.9
License-File: LICENSE.md
Requires-Dist: numpy >=1.23
Requires-Dist: tqdm >=4.0.0
Requires-Dist: torch >=2.1.0
Requires-Dist: torchaudio >=2.1.0
Requires-Dist: transformers >=4.28.0
